streamlit_octostar_utils/__init__.py
streamlit_octostar_utils/api_crafter/__init__.py
streamlit_octostar_utils/api_crafter/celery.py
streamlit_octostar_utils/api_crafter/fastapi.py
streamlit_octostar_utils/api_crafter/nifi.py
streamlit_octostar_utils/api_crafter/parallelism.py
streamlit_octostar_utils/api_crafter/parser/__init__.py
streamlit_octostar_utils/api_crafter/parser/combine_fields.py
streamlit_octostar_utils/api_crafter/parser/entities_parser.py
streamlit_octostar_utils/api_crafter/parser/generics.py
streamlit_octostar_utils/api_crafter/parser/info.py
streamlit_octostar_utils/api_crafter/parser/linkchart_functions.py
streamlit_octostar_utils/api_crafter/parser/matches.py
streamlit_octostar_utils/api_crafter/parser/parameters.py
streamlit_octostar_utils/api_crafter/parser/rules.py
streamlit_octostar_utils/api_crafter/parser/signals.py
streamlit_octostar_utils/core/__init__.py
streamlit_octostar_utils/core/dict.py
streamlit_octostar_utils/core/filetypes.py
streamlit_octostar_utils/core/threading/__init__.py
streamlit_octostar_utils/core/threading/key_queue.py
streamlit_octostar_utils/core/timestamp.py
streamlit_octostar_utils/nlp/__init__.py
streamlit_octostar_utils/nlp/custom_recognizers.py
streamlit_octostar_utils/nlp/language.py
streamlit_octostar_utils/nlp/ner.py
streamlit_octostar_utils/octostar/__init__.py
streamlit_octostar_utils/octostar/client.py
streamlit_octostar_utils/octostar/context.py
streamlit_octostar_utils/octostar/permissions.py
streamlit_octostar_utils/ontology/__init__.py
streamlit_octostar_utils/ontology/inheritance.py
streamlit_octostar_utils/ontology/relationships.py
streamlit_octostar_utils/ontology/validation.py
streamlit_octostar_utils/style/__init__.py
streamlit_octostar_utils/style/common.py
streamlit_octostar_utils/threading/__init__.py
streamlit_octostar_utils/threading/async_task_manager.py
streamlit_octostar_utils/threading/session_callback_manager.py
streamlit_octostar_utils/threading/session_state_hot_swapper.py
streamlit_octostar_utils-0.4.0.dist-info/METADATA
streamlit_octostar_utils-0.4.0.dist-info/WHEEL
streamlit_octostar_utils-0.4.0.dist-info/licenses/LICENSE
streamlit_octostar_utils-0.4.0.dist-info/RECORD
